README.md
setup.py
studio_ghibli_api_sdk/__init__.py
studio_ghibli_api_sdk/api_client.py
studio_ghibli_api_sdk/configuration.py
studio_ghibli_api_sdk/rest.py
studio_ghibli_api_sdk.egg-info/PKG-INFO
studio_ghibli_api_sdk.egg-info/SOURCES.txt
studio_ghibli_api_sdk.egg-info/dependency_links.txt
studio_ghibli_api_sdk.egg-info/requires.txt
studio_ghibli_api_sdk.egg-info/top_level.txt
studio_ghibli_api_sdk/api/__init__.py
studio_ghibli_api_sdk/api/films_api.py
studio_ghibli_api_sdk/api/locations_api.py
studio_ghibli_api_sdk/api/people_api.py
studio_ghibli_api_sdk/api/species_api.py
studio_ghibli_api_sdk/api/vehicles_api.py
studio_ghibli_api_sdk/models/__init__.py
studio_ghibli_api_sdk/models/error.py
studio_ghibli_api_sdk/models/films.py
studio_ghibli_api_sdk/models/locations.py
studio_ghibli_api_sdk/models/people.py
studio_ghibli_api_sdk/models/species.py
studio_ghibli_api_sdk/models/vehicles.py
test/__init__.py
test/test_error.py
test/test_films.py
test/test_films_api.py
test/test_locations.py
test/test_locations_api.py
test/test_people.py
test/test_people_api.py
test/test_species.py
test/test_species_api.py
test/test_vehicles.py
test/test_vehicles_api.py