Metadata-Version: 1.0
Name: studio-ghibli-api-sdk
Version: 1.0.3
Summary: Studio Ghibli API
Home-page: https://pypi.org/project/studio_ghibli_api_sdk/
Author: UNKNOWN
Author-email: UNKNOWN
License: UNKNOWN
Keywords: Swagger,Studio Ghibli API
Platform: UNKNOWN
